CHANGES.rst
CONTRIBUTORS.rst
MANIFEST.in
README.rst
setup.cfg
setup.py
docs/LICENSE.GPL
docs/LICENSE.rst
docs/index.rst
docs/recaptcha-contact-form.png
docs/recaptcha-settings.png
src/collective/__init__.py
src/collective.recaptchacontactform.egg-info/PKG-INFO
src/collective.recaptchacontactform.egg-info/SOURCES.txt
src/collective.recaptchacontactform.egg-info/dependency_links.txt
src/collective.recaptchacontactform.egg-info/entry_points.txt
src/collective.recaptchacontactform.egg-info/namespace_packages.txt
src/collective.recaptchacontactform.egg-info/not-zip-safe
src/collective.recaptchacontactform.egg-info/requires.txt
src/collective.recaptchacontactform.egg-info/top_level.txt
src/collective/recaptchacontactform/__init__.py
src/collective/recaptchacontactform/configure.zcml
src/collective/recaptchacontactform/contactformextender.py
src/collective/recaptchacontactform/interfaces.py
src/collective/recaptchacontactform/setuphandlers.py
src/collective/recaptchacontactform/testing.py
src/collective/recaptchacontactform/locales/collective.recaptchacontactform.pot
src/collective/recaptchacontactform/locales/update.sh
src/collective/recaptchacontactform/profiles/default/browserlayer.xml
src/collective/recaptchacontactform/profiles/default/metadata.xml
src/collective/recaptchacontactform/profiles/default/registry.xml
src/collective/recaptchacontactform/profiles/uninstall/browserlayer.xml
src/collective/recaptchacontactform/tests/__init__.py
src/collective/recaptchacontactform/tests/test_robot.py
src/collective/recaptchacontactform/tests/test_setup.py
src/collective/recaptchacontactform/tests/robot/test_example.robot