Metadata-Version: 1.1
Name: collective.recaptchacontactform
Version: 1.0a2
Summary: Protect the Plone contact form with ReCaptcha 2 from spam.
Home-page: https://pypi.python.org/pypi/collective.recaptchacontactform
Author: kitconcept GmbH
Author-email: info@kitconcept.com
License: GPL version 2
Keywords: Python Plone
Platform: UNKNOWN
Classifier: Environment :: Web Environment
Classifier: Framework :: Plone
Classifier: Framework :: Plone :: 5.0
Classifier: Programming Language :: Python
Classifier: Programming Language :: Python :: 2.7
Classifier: Operating System :: OS Independent
Classifier: License :: OSI Approved :: GNU General Public License v2 (GPLv2)
